cattrs_basemodel/__init__.py
cattrs_basemodel/basemodel.py
cattrs_basemodel/factory.py
cattrs_basemodel-1.0.dist-info/LICENSE
cattrs_basemodel-1.0.dist-info/METADATA
cattrs_basemodel-1.0.dist-info/WHEEL
cattrs_basemodel-1.0.dist-info/top_level.txt
cattrs_basemodel-1.0.dist-info/RECORD
