Metadata-Version: 2.1
Name: cattrs-basemodel
Version: 1.0
Summary: BaseModel for cattrs package which provide (un)structure methods to your models
Home-page: https://github.com/dail45/cattrs_basemodel
Author: dail45
Keywords: attrs cattrs basemodel json serialize deserialize
Classifier: Programming Language :: Python :: 3.11
Classifier: License :: OSI Approved :: MIT License
Classifier: Operating System :: OS Independent
Requires: cattrs
Requires-Python: >=3.6
License-File: LICENSE
